susi_lib/__init__.py
susi_lib/__main__.py
susi_lib/_version.py
susi_lib/dictionary.py
susi_lib/finder.py
susi_lib/regex.py
susi_lib/word_finder_cli.py
susi_lib/functions/__init__.py
susi_lib/functions/functions.py
susi_lib/types/__init__.py
susi_lib/types/braille.py
susi_lib/types/morse.py
susi_lib/types/number_systems.py
susi_lib/types/semaphore.py
susi_lib/types/symbols.py
susi_lib-1.2.5.dist-info/METADATA
susi_lib-1.2.5.dist-info/WHEEL
susi_lib-1.2.5.dist-info/entry_points.txt
susi_lib-1.2.5.dist-info/licenses/LICENSE
susi_lib-1.2.5.dist-info/RECORD
