Metadata-Version: 2.3
Name: susi-lib
Version: 1.2.5
Summary: Library for SuŠi organizers
Project-URL: Homepage, https://github.com/olilag/susi-lib
Author-email: Oliver Lago <oliver.oli.lago@gmail.com>
License-File: LICENSE
Classifier: Intended Audience :: Other Audience
Classifier: License :: OSI Approved :: MIT License
Classifier: Operating System :: OS Independent
Classifier: Programming Language :: Python
Classifier: Programming Language :: Python :: 3
Classifier: Programming Language :: Python :: 3.10
Classifier: Programming Language :: Python :: 3.11
Classifier: Programming Language :: Python :: 3.12
Requires-Python: >=3.10
Requires-Dist: platformdirs
Requires-Dist: typing-extensions; python_version < '3.11'
